verilator_mem_if/__init__.py
verilator_mem_if/_version.py
verilator_mem_if/backdoor.py
verilator_mem_if/backdoor_memory_interface.py
verilator_mem_if/conversion.py
verilator_mem_if/gdb/__init__.py
verilator_mem_if/gdb/commands.py
verilator_mem_if/gdb/parameters.py
verilator_mem_if/gdb/extensions/__init__.py
verilator_mem_if/gdb/extensions/memory.py
verilator_mem_if-0.1.5.dist-info/LICENSE
verilator_mem_if-0.1.5.dist-info/METADATA
verilator_mem_if-0.1.5.dist-info/WHEEL
verilator_mem_if-0.1.5.dist-info/entry_points.txt
verilator_mem_if-0.1.5.dist-info/top_level.txt
verilator_mem_if-0.1.5.dist-info/RECORD
