Metadata-Version: 2.1
Name: verilator-mem-if
Version: 0.1.5
Summary: Useful backdoor memory access tools for Verilator simulations.
Author: Shareef Jalloq
Author-email: shareef.jalloq@idexbiometrics.com
License: MIT
Project-URL: homepage, https://github.com/idex-biometrics/verilator-mem-if
Keywords: verilator,simulation,opentitan,backdoor
Classifier: Programming Language :: Python :: 3
Classifier: License :: OSI Approved :: MIT License
Requires-Python: >=3.6
License-File: LICENSE
Requires-Dist: veriloghex
Requires-Dist: intelhex
Requires-Dist: bincopy
Requires-Dist: gdbundle-verilator-mem-if
